herbert/__init__.py
herbert/__main__.py
herbert/cli.py
herbert/constants.py
herbert/counter.py
herbert/error.py
herbert/interpreter.py
herbert/level.py
herbert/parser.py
herbert/ui.py
herbert/util.py
herbert_python-0.0.1a3.dist-info/LICENSE.txt
herbert_python-0.0.1a3.dist-info/METADATA
herbert_python-0.0.1a3.dist-info/WHEEL
herbert_python-0.0.1a3.dist-info/entry_points.txt
herbert_python-0.0.1a3.dist-info/top_level.txt
herbert_python-0.0.1a3.dist-info/RECORD
