Metadata-Version: 2.1
Name: herbert-python
Version: 0.0.1a3
Summary: A CLI version of the Herbert game from Imagine Cup.
Home-page: https://github.com/dwayne/herbert-python
Author: Dwayne Crooks
Author-email: me@dwaynecrooks.com
License: MIT
Keywords: herbert,imaginecup,game
Platform: UNKNOWN
Classifier: Development Status :: 3 - Alpha
Classifier: Environment :: Console
Classifier: Intended Audience :: Developers
Classifier: License :: OSI Approved :: MIT License
Classifier: Operating System :: POSIX :: Linux
Classifier: Programming Language :: Python
Classifier: Programming Language :: Python :: 3.7
Classifier: Programming Language :: Python :: Implementation :: CPython
Requires-Dist: lark-parser (==0.6.4)
